sunvox/__init__.py
sunvox/api.py
sunvox/dll.py
sunvox/macros.py
sunvox/process.py
sunvox/processor.py
sunvox/slot.py
sunvox/types.py
sunvox/buffered/__init__.py
sunvox/buffered/process.py
sunvox/buffered/processor.py
sunvox/buffered/shm.py
sunvox/lib/copy-libs.sh
sunvox/lib/linux/lib_arm/sunvox.so
sunvox/lib/linux/lib_arm64/sunvox.so
sunvox/lib/linux/lib_x86/sunvox.so
sunvox/lib/linux/lib_x86_64/sunvox.so
sunvox/lib/macos/lib_arm64/sunvox.dylib
sunvox/lib/macos/lib_x86_64/sunvox.dylib
sunvox/lib/windows/lib_x86/sunvox.dll
sunvox/lib/windows/lib_x86_64/sunvox.dll
sunvox/tools/__init__.py
sunvox/tools/export.py
sunvox_dll_python-0.4.0.2.1.4.0.dist-info/METADATA
sunvox_dll_python-0.4.0.2.1.4.0.dist-info/WHEEL
sunvox_dll_python-0.4.0.2.1.4.0.dist-info/licenses/AUTHORS.rst
sunvox_dll_python-0.4.0.2.1.4.0.dist-info/licenses/LICENSE
sunvox_dll_python-0.4.0.2.1.4.0.dist-info/RECORD
