Metadata-Version: 2.4
Name: sunvox-dll-python
Version: 0.4.0.2.1.4.0
Summary: Python ctypes-based wrapper for the SunVox library
Author-email: Matthew Scott <matt@11craft.com>
License-File: AUTHORS.rst
License-File: LICENSE
Requires-Python: >=3.9
Provides-Extra: buffered
Requires-Dist: numpy>=2.0.2; extra == 'buffered'
Provides-Extra: docs
Requires-Dist: plantweb>=1.3.0; extra == 'docs'
Requires-Dist: radiant-voices>=1.0.3; extra == 'docs'
Requires-Dist: sphinx-rtd-theme>=3.0.2; extra == 'docs'
Requires-Dist: sphinx>=7.4.7; extra == 'docs'
Provides-Extra: tools
Requires-Dist: numpy>=2.0.2; extra == 'tools'
Requires-Dist: scipy>=1.13.1; extra == 'tools'
Requires-Dist: tqdm>=4.67.1; extra == 'tools'
